{
  "id": 57,
  "name": "シュガーラッシュ",
  "description": "ジンジャーブレッド城からルートビア海まで、そしてリコリス山脈からグミの森まで、お菓子王国に栄光あれ！",
  "skins": [
    {
      "id": 9007,
      "name": "闇の飴細工フィドルスティックス",
      "rarity": "kNoRarity",
      "isBase": false
    },
    {
      "id": 26006,
      "name": "シュガーラッシュ ジリアン",
      "rarity": "kEpic",
      "isBase": false
    },
    {
      "id": 28008,
      "name": "シュガーラッシュ イブリン",
      "rarity": "kEpic",
      "isBase": false
    },
    {
      "id": 78002,
      "name": "ロリポッピー",
      "rarity": "kNoRarity",
      "isBase": false
    },
    {
      "id": 115014,
      "name": "シュガーラッシュ ジグス",
      "rarity": "kEpic",
      "isBase": false
    },
    {
      "id": 117001,
      "name": "ほろ苦ルル",
      "rarity": "kNoRarity",
      "isBase": false
    },
    {
      "id": 201024,
      "name": "シュガーラッシュ ブラウム",
      "rarity": "kEpic",
      "isBase": false
    },
    {
      "id": 427001,
      "name": "お菓子の王様アイバーン",
      "rarity": "kEpic",
      "isBase": false
    }
  ]
}