{
  "id": 147,
  "name": "星籁歌姬",
  "alias": "Seraphine",
  "squarePortraitPath": "/lol-game-data/assets/v1/champion-icons/147.png",
  "roles": [
    "support",
    "mage"
  ],
  "skins": [
    {
      "id": 147000,
      "name": "星籁歌姬",
      "rarity": "kNoRarity",
      "isBase": true
    },
    {
      "id": 147001,
      "name": "K/DA ALL OUT 萨勒芬妮 独立音乐人",
      "rarity": "kUltimate",
      "isBase": false
    },
    {
      "id": 147004,
      "name": "神凰行者 幽羽玄凰 萨勒芬妮",
      "rarity": "kEpic",
      "isBase": false
    },
    {
      "id": 147014,
      "name": "海之歌 萨勒芬妮",
      "rarity": "kNoRarity",
      "isBase": false
    },
    {
      "id": 147015,
      "name": "至臻 海之歌 萨勒芬妮",
      "rarity": "kNoRarity",
      "isBase": false
    },
    {
      "id": 147024,
      "name": "花仙子 萨勒芬妮",
      "rarity": "kEpic",
      "isBase": false
    },
    {
      "id": 147034,
      "name": "星之守护者 萨勒芬妮",
      "rarity": "kEpic",
      "isBase": false
    },
    {
      "id": 147043,
      "name": "幻灵白鸽 萨勒芬妮",
      "rarity": "kLegendary",
      "isBase": false
    },
    {
      "id": 147050,
      "name": "点心宝贝 萨勒芬妮",
      "rarity": "kEpic",
      "isBase": false
    }
  ]
}