{
  "id": 134,
  "name": "暗黑元首",
  "alias": "Syndra",
  "squarePortraitPath": "/lol-game-data/assets/v1/champion-icons/134.png",
  "roles": [
    "mage"
  ],
  "skins": [
    {
      "id": 134000,
      "name": "暗黑元首",
      "rarity": "kNoRarity",
      "isBase": true,
      "wikiPrice": "880",
      "wikiReleaseDate": "2012-09-12T00:00:00.000Z"
    },
    {
      "id": 134001,
      "name": "仲裁圣女 辛德拉",
      "rarity": "kNoRarity",
      "isBase": false,
      "wikiPrice": "975",
      "wikiReleaseDate": "2012-09-12T00:00:00.000Z"
    },
    {
      "id": 134002,
      "name": "亚特兰蒂斯 辛德拉",
      "rarity": "kNoRarity",
      "isBase": false,
      "wikiPrice": "975",
      "wikiReleaseDate": "2014-04-29T00:00:00.000Z"
    },
    {
      "id": 134003,
      "name": "方块王后 辛德拉",
      "rarity": "kNoRarity",
      "isBase": false,
      "wikiPrice": "750",
      "wikiReleaseDate": "2015-05-20T00:00:00.000Z"
    },
    {
      "id": 134004,
      "name": "冰雪女神 辛德拉",
      "rarity": "kEpic",
      "isBase": false,
      "wikiPrice": "1350",
      "wikiReleaseDate": "2015-12-10T00:00:00.000Z"
    },
    {
      "id": 134005,
      "name": "SKT T1 辛德拉",
      "rarity": "kEpic",
      "isBase": false,
      "wikiPrice": "1350",
      "wikiReleaseDate": "2017-06-27T00:00:00.000Z"
    },
    {
      "id": 134006,
      "name": "星之守护者 辛德拉",
      "rarity": "kEpic",
      "isBase": false,
      "wikiPrice": "1350",
      "wikiReleaseDate": "2017-09-06T00:00:00.000Z"
    },
    {
      "id": 134007,
      "name": "泳池派对 辛德拉",
      "rarity": "kEpic",
      "isBase": false,
      "wikiPrice": "1350",
      "wikiReleaseDate": "2020-07-02T00:00:00.000Z"
    },
    {
      "id": 134016,
      "name": "幽梦玫瑰 辛德拉",
      "rarity": "kEpic",
      "isBase": false,
      "wikiPrice": "1350",
      "wikiReleaseDate": "2021-02-11T00:00:00.000Z"
    },
    {
      "id": 134025,
      "name": "魅惑女巫 辛德拉",
      "rarity": "kEpic",
      "isBase": false,
      "wikiPrice": "1350",
      "wikiReleaseDate": "2021-10-07T00:00:00.000Z"
    },
    {
      "id": 134034,
      "name": "至臻 星之守护者 辛德拉",
      "rarity": "kMythic",
      "isBase": false,
      "wikiPrice": "Special",
      "wikiReleaseDate": "2022-07-28T00:00:00.000Z"
    },
    {
      "id": 134044,
      "name": "灵魂莲华 辛德拉",
      "rarity": "kEpic",
      "isBase": false,
      "wikiPrice": "1350",
      "wikiReleaseDate": "2022-10-06T00:00:00.000Z"
    },
    {
      "id": 134054,
      "name": "魔女 辛德拉",
      "rarity": "kEpic",
      "isBase": false,
      "wikiPrice": "1350",
      "wikiReleaseDate": "2023-10-25T00:00:00.000Z"
    },
    {
      "id": 134065,
      "name": "点心宝贝 辛德拉",
      "rarity": "kEpic",
      "isBase": false,
      "wikiPrice": "1350",
      "wikiReleaseDate": "2025-02-05T00:00:00.000Z"
    }
  ]
}