{
  "id": 20026,
  "contentId": "8531c163-7acf-4707-8063-7677febf7106",
  "isBase": false,
  "name": "努努和嗡朗普",
  "splashPath": "/lol-game-data/assets/ASSETS/Characters/Nunu/Skins/Skin26/Images/nunu_splash_centered_26.jpg",
  "uncenteredSplashPath": "/lol-game-data/assets/ASSETS/Characters/Nunu/Skins/Skin26/Images/nunu_splash_uncentered_26.jpg",
  "tilePath": "/lol-game-data/assets/ASSETS/Characters/Nunu/Skins/Skin26/Images/nunu_splash_tile_26.jpg",
  "loadScreenPath": "/lol-game-data/assets/ASSETS/Characters/Nunu/Skins/Skin26/NunuLoadscreen_26.jpg",
  "skinType": "",
  "rarity": "kEpic",
  "isLegacy": false,
  "splashVideoPath": null,
  "collectionSplashVideoPath": null,
  "collectionCardHoverVideoPath": null,
  "featuresText": null,
  "chromaPath": "/lol-game-data/assets/v1/champion-chroma-images/20/20026.png",
  "chromas": [
    {
      "id": 20027,
      "name": "努努和嗡朗普",
      "contentId": "2d4d9b2b-a0c0-4c5f-b6ad-5be78e498c08",
      "chromaPath": "/lol-game-data/assets/v1/champion-chroma-images/20/20027.png",
      "colors": [
        "#D33528",
        "#D33528"
      ],
      "descriptions": [
        {
          "region": "riot",
          "description": "於 2022 年以組合包限定商品的形式發行。"
        }
      ],
      "rarities": [
        {
          "region": "riot",
          "rarity": 1
        }
      ]
    },
    {
      "id": 20028,
      "name": "努努和嗡朗普",
      "contentId": "c49fb9e6-f7d7-421f-a54e-7ccc17c04776",
      "chromaPath": "/lol-game-data/assets/v1/champion-chroma-images/20/20028.png",
      "colors": [
        "#54209B",
        "#54209B"
      ],
      "descriptions": [],
      "rarities": []
    },
    {
      "id": 20029,
      "name": "努努和嗡朗普",
      "contentId": "bb8d3db4-9dc5-403e-b706-055f36636b32",
      "chromaPath": "/lol-game-data/assets/v1/champion-chroma-images/20/20029.png",
      "colors": [
        "#2756CE",
        "#2756CE"
      ],
      "descriptions": [],
      "rarities": []
    },
    {
      "id": 20030,
      "name": "努努和嗡朗普",
      "contentId": "7e499fbe-6097-4c55-bc1a-51dbd1f85dd5",
      "chromaPath": "/lol-game-data/assets/v1/champion-chroma-images/20/20030.png",
      "colors": [
        "#2DA130",
        "#2DA130"
      ],
      "descriptions": [],
      "rarities": []
    },
    {
      "id": 20031,
      "name": "努努和嗡朗普",
      "contentId": "02229c4f-24fb-417a-8dfa-9699ecadf128",
      "chromaPath": "/lol-game-data/assets/v1/champion-chroma-images/20/20031.png",
      "colors": [
        "#E58BA5",
        "#E58BA5"
      ],
      "descriptions": [],
      "rarities": [
        {
          "region": "TENCENT",
          "rarity": 1
        }
      ]
    },
    {
      "id": 20032,
      "name": "努努和嗡朗普",
      "contentId": "3d255ad9-b308-4b48-9727-13884c0d38b1",
      "chromaPath": "/lol-game-data/assets/v1/champion-chroma-images/20/20032.png",
      "colors": [
        "#ECF9F8",
        "#ECF9F8"
      ],
      "descriptions": [],
      "rarities": []
    },
    {
      "id": 20033,
      "name": "努努和嗡朗普",
      "contentId": "16847f79-ed43-4210-972a-b560fdc913bd",
      "chromaPath": "/lol-game-data/assets/v1/champion-chroma-images/20/20033.png",
      "colors": [
        "#27211C",
        "#27211C"
      ],
      "descriptions": [],
      "rarities": []
    },
    {
      "id": 20034,
      "name": "努努和嗡朗普",
      "contentId": "0ff0c812-b874-43fe-a445-75cc1fb31af6",
      "chromaPath": "/lol-game-data/assets/v1/champion-chroma-images/20/20034.png",
      "colors": [
        "#C1F2FF",
        "#C1F2FF"
      ],
      "descriptions": [],
      "rarities": []
    }
  ],
  "emblems": null,
  "regionRarityId": 0,
  "rarityGemPath": null,
  "skinLines": [
    {
      "id": 143
    }
  ],
  "description": "他們就像是兩心同體。呃……還是該說兩蜂同巢？",
  "wikiSkinData": {
    "id": 20026,
    "formatname": "Nunu & Beelump",
    "availability": "Available",
    "looteligible": true,
    "cost": 1350,
    "release": "2022-03-03",
    "set": [
      "Bees!"
    ],
    "neweffects": true,
    "newanimations": true,
    "newrecall": true,
    "chromas": {
      "Emerald": {
        "id": 30
      },
      "Obsidian": {
        "id": 33
      },
      "Pearl": {
        "id": 32
      },
      "Rainbow": {
        "id": 34
      },
      "Rose Quartz": {
        "id": 31
      },
      "Ruby": {
        "id": 27,
        "availability": "Bundle",
        "source": "Bundle",
        "distribution": "Bundle Exclusive"
      },
      "Sapphire": {
        "id": 29
      },
      "Tanzanite": {
        "id": 28
      }
    },
    "voiceactor": [
      "Lucas Jaye",
      "Jonathan Lipow"
    ],
    "splashartist": [
      "Horace 'Hozure' Hsu"
    ],
    "lore": "They're like two bees in a pod. Err… in a hive?"
  }
}