{
  "id": 82000,
  "contentId": "fda97726-46a1-4bca-9b7e-47be2b359878",
  "isBase": true,
  "name": "魔鬥凱薩",
  "splashPath": "/lol-game-data/assets/ASSETS/Characters/Mordekaiser/Skins/Base/Images/mordekaiser_splash_centered_0.jpg",
  "uncenteredSplashPath": "/lol-game-data/assets/ASSETS/Characters/Mordekaiser/Skins/Base/Images/mordekaiser_splash_uncentered_0.jpg",
  "tilePath": "/lol-game-data/assets/ASSETS/Characters/Mordekaiser/Skins/Base/Images/mordekaiser_splash_tile_0.jpg",
  "loadScreenPath": "/lol-game-data/assets/ASSETS/Characters/Mordekaiser/Skins/Base/MordekaiserLoadscreen.jpg",
  "skinType": "",
  "rarity": "kNoRarity",
  "isLegacy": false,
  "splashVideoPath": null,
  "collectionSplashVideoPath": null,
  "collectionCardHoverVideoPath": null,
  "featuresText": null,
  "chromaPath": null,
  "emblems": null,
  "regionRarityId": 0,
  "rarityGemPath": null,
  "skinLines": null,
  "description": null,
  "wikiSkinData": {
    "id": 82000,
    "availability": "Available",
    "looteligible": true,
    "cost": 585,
    "release": "2010-02-24",
    "voiceactor": [
      "Fred Tatasciore"
    ],
    "splashartist": [
      "Alex 'alexplank' Flores"
    ],
    "lore": "Twice slain and thrice born, Mordekaiser is a brutal warlord from a foregone epoch who uses his necromantic sorcery to bind souls into an eternity of servitude. Few now remain who remember his earlier conquests, or know the true extent of his powers"
  }
}