{
  "id": 84001,
  "contentId": "328fc0ae-9f6d-44c8-972d-833a061bb74a",
  "isBase": false,
  "name": "蜂刺 阿卡莉",
  "splashPath": "/lol-game-data/assets/ASSETS/Characters/Akali/Skins/Skin01/Images/akali_splash_centered_1.jpg",
  "uncenteredSplashPath": "/lol-game-data/assets/ASSETS/Characters/Akali/Skins/Skin01/Images/akali_splash_uncentered_1.jpg",
  "tilePath": "/lol-game-data/assets/ASSETS/Characters/Akali/Skins/Skin01/Images/akali_splash_tile_1.jpg",
  "loadScreenPath": "/lol-game-data/assets/ASSETS/Characters/Akali/Skins/Skin01/AkaliLoadscreen_1.jpg",
  "skinType": "",
  "rarity": "kNoRarity",
  "isLegacy": true,
  "splashVideoPath": null,
  "collectionSplashVideoPath": null,
  "collectionCardHoverVideoPath": null,
  "featuresText": null,
  "chromaPath": null,
  "emblems": null,
  "regionRarityId": 0,
  "rarityGemPath": null,
  "skinLines": null,
  "description": "偉大的蜂刺之序遵循著一套殘酷且歷史悠久的訓練體系，教導門徒要像大黃蜂那樣兇狠地不斷進攻。阿卡莉是他們其中最偉大的冠軍，且她打算把這門藝術推向另一個新的高度。",
  "wikiSkinData": {
    "id": 84001,
    "availability": "Legacy",
    "looteligible": true,
    "cost": 520,
    "release": "2010-05-11",
    "retired": "2014-12-02",
    "voiceactor": [
      "Krizia Bajos"
    ],
    "splashartist": [
      "Pyeongjun Park"
    ],
    "lore": "The Order of the Great Sparrow Bee follows a brutal, time-honored training regimen, teaching students to sting with the ferocity and ceaselessness of a hornet. Akali is their greatest champion, and she intends to take the art to even greater heights."
  }
}