{
  "id": 209,
  "name": "Chosen of the Wolf",
  "description": "When the young warleader Ambessa falls in battle, she is granted a vision of Volrachnun, a hallowed afterlife for worthy followers of the Wolf. All who are welcomed into this haven must join the Eternal Chase, finding bliss in battle and joyfully challenging their fellow chosen warriors in a never-ending hunt.",
  "skins": [
    {
      "id": 50032,
      "name": "Chosen of the Wolf Swain",
      "rarity": "kEpic",
      "isBase": false
    },
    {
      "id": 50033,
      "name": "Prestige Chosen of the Wolf Swain",
      "rarity": "kMythic",
      "isBase": false
    },
    {
      "id": 55059,
      "name": "Chosen of the Wolf Katarina",
      "rarity": "kEpic",
      "isBase": false
    },
    {
      "id": 80038,
      "name": "Chosen of the Wolf Pantheon",
      "rarity": "kEpic",
      "isBase": false
    },
    {
      "id": 203034,
      "name": "Chosen of the Wolf Kindred",
      "rarity": "kEpic",
      "isBase": false
    },
    {
      "id": 799001,
      "name": "Chosen of the Wolf Ambessa",
      "rarity": "kLegendary",
      "isBase": false
    }
  ]
}