{
  "id": 14,
  "name": "賽恩",
  "alias": "Sion",
  "squarePortraitPath": "/lol-game-data/assets/v1/champion-icons/14.png",
  "roles": [
    "tank",
    "fighter"
  ],
  "skins": [
    {
      "id": 14000,
      "name": "賽恩",
      "rarity": "kNoRarity",
      "isBase": true,
      "wikiPrice": "585",
      "wikiReleaseDate": "2009-02-21T00:00:00.000Z"
    },
    {
      "id": 14001,
      "name": "海克斯科技 賽恩",
      "rarity": "kNoRarity",
      "isBase": false,
      "wikiPrice": "520",
      "wikiReleaseDate": "2010-06-01T00:00:00.000Z"
    },
    {
      "id": 14002,
      "name": "蠻族戰士  賽恩",
      "rarity": "kNoRarity",
      "isBase": false,
      "wikiPrice": "750",
      "wikiReleaseDate": "2010-09-26T00:00:00.000Z"
    },
    {
      "id": 14003,
      "name": "歡樂伐木工 賽恩",
      "rarity": "kNoRarity",
      "isBase": false,
      "wikiPrice": "520",
      "wikiReleaseDate": "2011-01-24T00:00:00.000Z"
    },
    {
      "id": 14004,
      "name": "戰爭惡魔 賽恩",
      "rarity": "kNoRarity",
      "isBase": false,
      "wikiPrice": "975",
      "wikiReleaseDate": "2011-07-18T00:00:00.000Z"
    },
    {
      "id": 14005,
      "name": "機甲特急 賽恩",
      "rarity": "kLegendary",
      "isBase": false,
      "wikiPrice": "1820",
      "wikiReleaseDate": "2016-04-13T00:00:00.000Z"
    },
    {
      "id": 14014,
      "name": "文明末日 賽恩",
      "rarity": "kEpic",
      "isBase": false,
      "wikiPrice": "1350",
      "wikiReleaseDate": "2020-04-09T00:00:00.000Z"
    },
    {
      "id": 14022,
      "name": "黯雪冽斧 賽恩 ",
      "rarity": "kEpic",
      "isBase": false,
      "wikiPrice": "1350",
      "wikiReleaseDate": "2021-04-15T00:00:00.000Z"
    },
    {
      "id": 14030,
      "name": "西域牛仔 賽恩",
      "rarity": "kEpic",
      "isBase": false,
      "wikiPrice": "1350",
      "wikiReleaseDate": "2022-05-26T00:00:00.000Z"
    },
    {
      "id": 14040,
      "name": "星河聖騎 賽恩",
      "rarity": "kEpic",
      "isBase": false,
      "wikiPrice": "1350",
      "wikiReleaseDate": "2023-08-30T00:00:00.000Z"
    },
    {
      "id": 14049,
      "name": "大角鬥賽 賽恩",
      "rarity": "kNoRarity",
      "isBase": false,
      "wikiPrice": "Special",
      "wikiReleaseDate": "2025-03-05T00:00:00.000Z"
    }
  ]
}