{
  "id": 86022,
  "contentId": "352dfcec-bd79-4d37-94e2-d674be19a825",
  "isBase": false,
  "name": "메카 삼국 가렌",
  "splashPath": "/lol-game-data/assets/ASSETS/Characters/Garen/Skins/Skin22/Images/garen_splash_centered_22.jpg",
  "uncenteredSplashPath": "/lol-game-data/assets/ASSETS/Characters/Garen/Skins/Skin22/Images/garen_splash_uncentered_22.jpg",
  "tilePath": "/lol-game-data/assets/ASSETS/Characters/Garen/Skins/Skin22/Images/garen_splash_tile_22.jpg",
  "loadScreenPath": "/lol-game-data/assets/ASSETS/Characters/Garen/Skins/Skin22/GarenLoadscreen_22.jpg",
  "loadScreenVintagePath": "/lol-game-data/assets/ASSETS/Characters/Garen/Skins/Skin22/GarenLoadscreen_22_LE.jpg",
  "skinType": "",
  "rarity": "kEpic",
  "isLegacy": false,
  "splashVideoPath": null,
  "collectionSplashVideoPath": null,
  "collectionCardHoverVideoPath": null,
  "featuresText": null,
  "chromaPath": null,
  "emblems": null,
  "regionRarityId": 0,
  "rarityGemPath": null,
  "skinLines": [
    {
      "id": 127
    }
  ],
  "description": "무자비한 장군이자 군주였던 가렌은 군대를 이끌고 승승장구하며 버센치아 왕국의 초석을 깔았습니다. 하지만 거대한 괴수들이 나타나자 가렌은 삼국 통일의 꿈을 잠시 접어 두기로 했죠. 그는 새롭게 개량한 아발론을 이끌고 한때 적이었던 자들과 힘을 합쳐 인류를 위해 싸웁니다.",
  "wikiSkinData": {
    "id": 86022,
    "availability": "Available",
    "looteligible": true,
    "cost": 1350,
    "release": "2020-01-15",
    "set": [
      "Mecha Kingdoms"
    ],
    "neweffects": true,
    "newanimations": true,
    "newrecall": true,
    "filter": true,
    "voiceactor": [
      "Jamieson Price"
    ],
    "splashartist": [
      "Clare Wong",
      "West Studio"
    ],
    "lore": "Once a ruthless warlord, Garen led his armies to victory after victory, laying the foundations for the Vercentia Kingdom. When the leviathans appeared out of nowhere, he opted to put aside his dream of uniting all the Great Kingdoms under his rule, and instead to march his newly-fashioned Avalon alongside his former enemies for the sake of humanity."
  }
}