{
  "id": 163003,
  "contentId": "a711221f-5de8-45c5-ad93-851fe663dbca",
  "isBase": false,
  "name": "プールパーティ タリヤ",
  "splashPath": "/lol-game-data/assets/ASSETS/Characters/Taliyah/Skins/Skin03/Images/taliyah_splash_centered_3.jpg",
  "uncenteredSplashPath": "/lol-game-data/assets/ASSETS/Characters/Taliyah/Skins/Skin03/Images/taliyah_splash_uncentered_3.jpg",
  "tilePath": "/lol-game-data/assets/ASSETS/Characters/Taliyah/Skins/Skin03/Images/taliyah_splash_tile_3.jpg",
  "loadScreenPath": "/lol-game-data/assets/ASSETS/Characters/Taliyah/Skins/Skin03/TaliyahLoadscreen_3.jpg",
  "skinType": "",
  "rarity": "kEpic",
  "isLegacy": false,
  "splashVideoPath": null,
  "collectionSplashVideoPath": null,
  "collectionCardHoverVideoPath": null,
  "featuresText": null,
  "chromaPath": "/lol-game-data/assets/v1/champion-chroma-images/163/163003.png",
  "chromas": [
    {
      "id": 163004,
      "name": "プールパーティ タリヤ",
      "contentId": "be6cdff5-7615-4bc5-aa7f-57d373052d29",
      "chromaPath": "/lol-game-data/assets/v1/champion-chroma-images/163/163004.png",
      "colors": [
        "#D33528",
        "#D33528"
      ],
      "descriptions": [
        {
          "region": "riot",
          "description": "2020年にセット限定でリリース。"
        }
      ],
      "rarities": [
        {
          "region": "riot",
          "rarity": 1
        }
      ]
    },
    {
      "id": 163005,
      "name": "プールパーティ タリヤ",
      "contentId": "e2d87d0f-8f43-40be-90f8-1c3f46b9a64f",
      "chromaPath": "/lol-game-data/assets/v1/champion-chroma-images/163/163005.png",
      "colors": [
        "#6ABBEE",
        "#6ABBEE"
      ],
      "descriptions": [],
      "rarities": []
    },
    {
      "id": 163006,
      "name": "プールパーティ タリヤ",
      "contentId": "6e4fd670-2f12-44f9-8ab6-649e53dc82c4",
      "chromaPath": "/lol-game-data/assets/v1/champion-chroma-images/163/163006.png",
      "colors": [
        "#73BFBE",
        "#73BFBE"
      ],
      "descriptions": [],
      "rarities": []
    },
    {
      "id": 163007,
      "name": "プールパーティ タリヤ",
      "contentId": "e9f792f1-1ce0-48e1-839f-4920b0fa0458",
      "chromaPath": "/lol-game-data/assets/v1/champion-chroma-images/163/163007.png",
      "colors": [
        "#FFEE59",
        "#FFEE59"
      ],
      "descriptions": [],
      "rarities": []
    },
    {
      "id": 163008,
      "name": "プールパーティ タリヤ",
      "contentId": "9cd033f1-1d4a-46d4-89c8-2fd7d5441d5f",
      "chromaPath": "/lol-game-data/assets/v1/champion-chroma-images/163/163008.png",
      "colors": [
        "#B6E084",
        "#B6E084"
      ],
      "descriptions": [],
      "rarities": []
    },
    {
      "id": 163009,
      "name": "プールパーティ タリヤ",
      "contentId": "8d64a753-f88f-4e8d-930c-5dc254095069",
      "chromaPath": "/lol-game-data/assets/v1/champion-chroma-images/163/163009.png",
      "colors": [
        "#E58BA5",
        "#E58BA5"
      ],
      "descriptions": [],
      "rarities": [
        {
          "region": "TENCENT",
          "rarity": 1
        }
      ]
    },
    {
      "id": 163010,
      "name": "プールパーティ タリヤ",
      "contentId": "1d4ad42f-b60c-4d47-a4c6-6c70e1d381c2",
      "chromaPath": "/lol-game-data/assets/v1/champion-chroma-images/163/163010.png",
      "colors": [
        "#9C68D7",
        "#9C68D7"
      ],
      "descriptions": [],
      "rarities": []
    }
  ],
  "emblems": null,
  "regionRarityId": 0,
  "rarityGemPath": null,
  "skinLines": [
    {
      "id": 15
    }
  ],
  "description": "タリヤは以前、波に乗れず途方に暮れていたジャーヴァンにサーフィンをレクチャーしたことがある。「ピットに叩きつけられる」「チューブライドする」「バレルをメイク」といった専門用語を使ったのでジャーヴァンは絶対理解してないだろうな、とタリヤは確信している。",
  "wikiSkinData": {
    "id": 163003,
    "availability": "Available",
    "looteligible": true,
    "cost": 1350,
    "release": "2020-07-02",
    "set": [
      "Pool Party"
    ],
    "neweffects": true,
    "newanimations": true,
    "newrecall": true,
    "chromas": {
      "Amethyst": {
        "id": 10
      },
      "Aquamarine": {
        "id": 5
      },
      "Catseye": {
        "id": 7
      },
      "Peridot": {
        "id": 8
      },
      "Rose Quartz": {
        "id": 9
      },
      "Ruby": {
        "id": 4,
        "availability": "Bundle",
        "source": "Bundle",
        "distribution": "Bundle Exclusive"
      },
      "Turquoise": {
        "id": 6
      }
    },
    "voiceactor": [
      "Erica Lindbeck"
    ],
    "splashartist": [
      "Sean 'Raiko' Tay",
      "West Studio"
    ],
    "lore": "Taliyah once attempted to describe surfboarding to a perplexed Jarvan, using such terms as “get pitted”, “tubular”, and “ride the barrel”. She's pretty sure he still has no idea what she was talking about."
  }
}