{
  "id": 84015,
  "contentId": "60242bab-0053-4f52-a7de-525c6e96089b",
  "isBase": false,
  "name": "True Damage アカリ",
  "splashPath": "/lol-game-data/assets/ASSETS/Characters/Akali/Skins/Skin15/Images/akali_splash_centered_15.jpg",
  "uncenteredSplashPath": "/lol-game-data/assets/ASSETS/Characters/Akali/Skins/Skin15/Images/akali_splash_uncentered_15.jpg",
  "tilePath": "/lol-game-data/assets/ASSETS/Characters/Akali/Skins/Skin15/Images/akali_splash_tile_15.jpg",
  "loadScreenPath": "/lol-game-data/assets/ASSETS/Characters/Akali/Skins/Skin15/AkaliLoadscreen_15.jpg",
  "loadScreenVintagePath": "/lol-game-data/assets/ASSETS/Characters/Akali/Skins/Skin15/AkaliLoadscreen_15_LE.jpg",
  "skinType": "",
  "rarity": "kEpic",
  "isLegacy": false,
  "splashVideoPath": null,
  "collectionSplashVideoPath": null,
  "collectionCardHoverVideoPath": null,
  "featuresText": null,
  "chromaPath": "/lol-game-data/assets/v1/champion-chroma-images/84/84015.png",
  "chromas": [
    {
      "id": 84025,
      "name": "True Damage アカリ",
      "contentId": "940f6b17-be76-423a-84e9-60eaae20ad82",
      "chromaPath": "/lol-game-data/assets/v1/champion-chroma-images/84/84025.png",
      "colors": [
        "#D33528",
        "#D33528"
      ],
      "descriptions": [
        {
          "region": "riot",
          "description": "2019年にセット限定でリリース。"
        }
      ],
      "rarities": [
        {
          "region": "riot",
          "rarity": 1
        }
      ]
    },
    {
      "id": 84026,
      "name": "True Damage アカリ",
      "contentId": "c86cf67e-5732-4a85-9f89-ad8e4bde2790",
      "chromaPath": "/lol-game-data/assets/v1/champion-chroma-images/84/84026.png",
      "colors": [
        "#FFEE59",
        "#FFEE59"
      ],
      "descriptions": [],
      "rarities": []
    },
    {
      "id": 84027,
      "name": "True Damage アカリ",
      "contentId": "9dfb6406-fd85-4dac-a7b1-9e65fa3b1360",
      "chromaPath": "/lol-game-data/assets/v1/champion-chroma-images/84/84027.png",
      "colors": [
        "#2DA130",
        "#2DA130"
      ],
      "descriptions": [
        {
          "region": "riot",
          "description": "インフルエンサーの視聴者プレゼントで入手。"
        }
      ],
      "rarities": [
        {
          "region": "riot",
          "rarity": 1
        }
      ]
    },
    {
      "id": 84028,
      "name": "True Damage アカリ",
      "contentId": "accb7f93-8389-43cb-a3ec-796e491cf64c",
      "chromaPath": "/lol-game-data/assets/v1/champion-chroma-images/84/84028.png",
      "colors": [
        "#2756CE",
        "#2756CE"
      ],
      "descriptions": [],
      "rarities": []
    },
    {
      "id": 84029,
      "name": "True Damage アカリ",
      "contentId": "21cd0f9b-089c-4341-a11d-0cabc5b42a58",
      "chromaPath": "/lol-game-data/assets/v1/champion-chroma-images/84/84029.png",
      "colors": [
        "#E58BA5",
        "#E58BA5"
      ],
      "descriptions": [],
      "rarities": [
        {
          "region": "TENCENT",
          "rarity": 1
        }
      ]
    },
    {
      "id": 84030,
      "name": "True Damage アカリ",
      "contentId": "f91bf6c0-9565-4cab-bacc-b461579a5cc0",
      "chromaPath": "/lol-game-data/assets/v1/champion-chroma-images/84/84030.png",
      "colors": [
        "#ECF9F8",
        "#ECF9F8"
      ],
      "descriptions": [],
      "rarities": []
    },
    {
      "id": 84031,
      "name": "True Damage アカリ",
      "contentId": "93226781-b880-4872-a4d2-961c77ef6bee",
      "chromaPath": "/lol-game-data/assets/v1/champion-chroma-images/84/84031.png",
      "colors": [
        "#BD1357",
        "#19182A"
      ],
      "descriptions": [
        {
          "region": "riot",
          "description": "2019年に戦利品限定アイテムとしてリリース。"
        }
      ],
      "rarities": [
        {
          "region": "riot",
          "rarity": 1
        }
      ]
    }
  ],
  "emblems": null,
  "regionRarityId": 0,
  "rarityGemPath": null,
  "skinLines": [
    {
      "id": 120
    }
  ],
  "description": "K/DAで世界的な成功を収めたあと、アカリは一流アーティストと新進気鋭のアーティストを集めて新たなスターグループ「True Damage」を結成することを自らの使命とし、ここにかつてないほど多彩な才能が集められたグループが誕生した。天性のリリシストに大物プロデューサー、伝説のボーカリストまで、その誰もが音楽業界に革命を起こす力を持っている。",
  "wikiPrice": "1350",
  "wikiReleaseDate": "2019-11-10T00:00:00.000Z"
}