{
  "id": 421026,
  "contentId": "d62b8b1f-2dfb-40a1-993f-0abea275bb1b",
  "isBase": false,
  "name": "海魔兽 雷克塞",
  "splashPath": "/lol-game-data/assets/ASSETS/Characters/RekSai/Skins/Skin26/Images/reksai_splash_centered_26.SKINS_RekSai_Skin26.jpg",
  "uncenteredSplashPath": "/lol-game-data/assets/ASSETS/Characters/RekSai/Skins/Skin26/Images/reksai_splash_uncentered_26.SKINS_RekSai_Skin26.jpg",
  "tilePath": "/lol-game-data/assets/ASSETS/Characters/RekSai/Skins/Skin26/Images/reksai_splash_tile_26.SKINS_RekSai_Skin26.jpg",
  "loadScreenPath": "/lol-game-data/assets/ASSETS/Characters/RekSai/Skins/Skin26/RekSaiLoadScreen_26.SKINS_RekSai_Skin26.jpg",
  "loadScreenVintagePath": "/lol-game-data/assets/ASSETS/Characters/RekSai/Skins/Skin26/RekSaiLoadScreen_26_LE.SKINS_RekSai_Skin26.jpg",
  "skinType": "",
  "rarity": "kEpic",
  "isLegacy": false,
  "splashVideoPath": null,
  "collectionSplashVideoPath": null,
  "collectionCardHoverVideoPath": null,
  "featuresText": null,
  "chromaPath": "/lol-game-data/assets/v1/champion-chroma-images/421/421026.png",
  "chromas": [
    {
      "id": 421027,
      "name": "海魔兽 雷克塞 威慑嘶吼",
      "contentId": "45207479-8f65-483c-9f1e-422d33028097",
      "chromaPath": "/lol-game-data/assets/v1/champion-chroma-images/421/421027.png",
      "colors": [
        "#D33528",
        "#D33528"
      ],
      "descriptions": [
        {
          "region": "riot",
          "description": "这个炫彩曾在2024年期间作为礼包专属发布。"
        }
      ],
      "rarities": [
        {
          "region": "riot",
          "rarity": 1
        }
      ]
    },
    {
      "id": 421028,
      "name": "海魔兽 雷克塞 呼啸俯冲",
      "contentId": "097d3603-9d8d-468b-8950-e70c9dd92c67",
      "chromaPath": "/lol-game-data/assets/v1/champion-chroma-images/421/421028.png",
      "colors": [
        "#FFEE59",
        "#FFEE59"
      ],
      "descriptions": [],
      "rarities": []
    },
    {
      "id": 421029,
      "name": "海魔兽 雷克塞 高傲气场",
      "contentId": "2cc5b2be-d142-48e1-b5a8-4ec51056bb28",
      "chromaPath": "/lol-game-data/assets/v1/champion-chroma-images/421/421029.png",
      "colors": [
        "#9C68D7",
        "#9C68D7"
      ],
      "descriptions": [],
      "rarities": []
    },
    {
      "id": 421030,
      "name": "海魔兽 雷克塞 无情背袭",
      "contentId": "14006db1-f64d-4de9-a410-374d2af08b41",
      "chromaPath": "/lol-game-data/assets/v1/champion-chroma-images/421/421030.png",
      "colors": [
        "#2756CE",
        "#2756CE"
      ],
      "descriptions": [],
      "rarities": []
    },
    {
      "id": 421031,
      "name": "海魔兽 雷克塞 无休冲击",
      "contentId": "acfb638d-23d2-4dc5-b0c1-53843c343bb0",
      "chromaPath": "/lol-game-data/assets/v1/champion-chroma-images/421/421031.png",
      "colors": [
        "#2DA130",
        "#2DA130"
      ],
      "descriptions": [
        {
          "region": "riot",
          "description": " "
        }
      ],
      "rarities": [
        {
          "region": "riot",
          "rarity": 1
        }
      ]
    },
    {
      "id": 421032,
      "name": "海魔兽 雷克塞 梦魇狂袭",
      "contentId": "d5ca55e3-61a0-4e26-b15f-908c9d674def",
      "chromaPath": "/lol-game-data/assets/v1/champion-chroma-images/421/421032.png",
      "colors": [
        "#E58BA5",
        "#E58BA5"
      ],
      "descriptions": [],
      "rarities": [
        {
          "region": "TENCENT",
          "rarity": 1
        }
      ]
    },
    {
      "id": 421033,
      "name": "海魔兽 雷克塞 折光遮蔽",
      "contentId": "a933ae30-8c96-49d9-b52e-9b9bac9f8a0b",
      "chromaPath": "/lol-game-data/assets/v1/champion-chroma-images/421/421033.png",
      "colors": [
        "#C1F2FF",
        "#C1F2FF"
      ],
      "descriptions": [],
      "rarities": []
    },
    {
      "id": 421034,
      "name": "海魔兽 雷克塞 黑云压城",
      "contentId": "862d9100-ffde-47f3-ab5c-b638a9244f27",
      "chromaPath": "/lol-game-data/assets/v1/champion-chroma-images/421/421034.png",
      "colors": [
        "#27211C",
        "#27211C"
      ],
      "descriptions": [],
      "rarities": []
    },
    {
      "id": 421035,
      "name": "海魔兽 雷克塞 深渊潜袭",
      "contentId": "b5b9e8f0-aaa5-4eee-b784-79f7ddd38788",
      "chromaPath": "/lol-game-data/assets/v1/champion-chroma-images/421/421035.png",
      "colors": [
        "#3BE98B",
        "#BABA9B"
      ],
      "descriptions": [
        {
          "region": "riot",
          "description": "这个炫彩曾在幻灵战队(2024)事件期间作为战利品专属发布。"
        }
      ],
      "rarities": [
        {
          "region": "riot",
          "rarity": 1
        }
      ]
    }
  ],
  "emblems": null,
  "regionRarityId": 0,
  "rarityGemPath": null,
  "skinLines": [
    {
      "id": 206
    }
  ],
  "description": "最终都市高筑护栏，保护其公民免受无穷尽的海魔人威胁。面对这些阻碍，雷克塞大笑起来——或者至少以大声、痛苦的尖叫的形式模仿笑声。她已经进化到可以在地下挖掘隧道，是理想的渗透者，也是第一个看到最终都市的海魔人……但肯定不是最后一个。",
  "wikiPrice": "1350",
  "wikiReleaseDate": "2024-07-17T00:00:00.000Z"
}