{
  "id": 19,
  "name": "ワーウィック",
  "alias": "Warwick",
  "squarePortraitPath": "/lol-game-data/assets/v1/champion-icons/19.png",
  "roles": [
    "fighter",
    "tank"
  ],
  "skins": [
    {
      "id": 19000,
      "name": "ワーウィック",
      "rarity": "kNoRarity",
      "isBase": true
    },
    {
      "id": 19001,
      "name": "銀狼ワーウィック",
      "rarity": "kNoRarity",
      "isBase": false
    },
    {
      "id": 19002,
      "name": "アーフ・ザ・マナティ",
      "rarity": "kNoRarity",
      "isBase": false
    },
    {
      "id": 19003,
      "name": "悪巧み中のワーウィック",
      "rarity": "kNoRarity",
      "isBase": false
    },
    {
      "id": 19004,
      "name": "ツンドラの狩人ワーウィック",
      "rarity": "kNoRarity",
      "isBase": false
    },
    {
      "id": 19005,
      "name": "獣王ワーウィック",
      "rarity": "kNoRarity",
      "isBase": false
    },
    {
      "id": 19006,
      "name": "火焔の牙ワーウィック",
      "rarity": "kNoRarity",
      "isBase": false
    },
    {
      "id": 19007,
      "name": "ハイエナ ワーウィック",
      "rarity": "kNoRarity",
      "isBase": false
    },
    {
      "id": 19008,
      "name": "略奪者ワーウィック",
      "rarity": "kNoRarity",
      "isBase": false
    },
    {
      "id": 19009,
      "name": "アーフウィック",
      "rarity": "kNoRarity",
      "isBase": false
    },
    {
      "id": 19010,
      "name": "月の守護者ワーウィック",
      "rarity": "kEpic",
      "isBase": false
    },
    {
      "id": 19016,
      "name": "PROJECT: Warwick",
      "rarity": "kEpic",
      "isBase": false
    },
    {
      "id": 19035,
      "name": "古の神ワーウィック",
      "rarity": "kEpic",
      "isBase": false
    },
    {
      "id": 19045,
      "name": "冬の祝福ワーウィック",
      "rarity": "kEpic",
      "isBase": false
    },
    {
      "id": 19046,
      "name": "プレステージ冬の祝福ワーウィック",
      "rarity": "kMythic",
      "isBase": false
    },
    {
      "id": 19056,
      "name": "Arcane ヴァンダー・ワーウィック",
      "rarity": "kEpic",
      "isBase": false
    }
  ]
}