{
  "id": 15061,
  "contentId": "f48f907d-6874-476e-a5cc-1797e923fe72",
  "isBase": false,
  "name": "Primal Ambush Sivir",
  "splashPath": "/lol-game-data/assets/ASSETS/Characters/Sivir/Skins/Skin61/Images/sivir_splash_centered_61.jpg",
  "uncenteredSplashPath": "/lol-game-data/assets/ASSETS/Characters/Sivir/Skins/Skin61/Images/sivir_splash_uncentered_61.jpg",
  "tilePath": "/lol-game-data/assets/ASSETS/Characters/Sivir/Skins/Skin61/Images/sivir_splash_tile_61.jpg",
  "loadScreenPath": "/lol-game-data/assets/ASSETS/Characters/Sivir/Skins/Skin61/SivirLoadScreen_61.jpg",
  "loadScreenVintagePath": "/lol-game-data/assets/ASSETS/Characters/Sivir/Skins/Skin61/SivirLoadScreen_61_LE.jpg",
  "skinType": "",
  "rarity": "kEpic",
  "isLegacy": false,
  "splashVideoPath": null,
  "collectionSplashVideoPath": null,
  "collectionCardHoverVideoPath": null,
  "featuresText": null,
  "chromaPath": "/lol-game-data/assets/v1/champion-chroma-images/15/15061.png",
  "chromas": [
    {
      "id": 15062,
      "name": "Primal Ambush Sivir",
      "contentId": "685b2065-2dc4-4441-9bbf-d62c93f0c640",
      "chromaPath": "/lol-game-data/assets/v1/champion-chroma-images/15/15062.png",
      "colors": [
        "#D33528",
        "#D33528"
      ],
      "descriptions": [
        {
          "region": "riot",
          "description": "This chroma was released as a bundle exclusive in 2024."
        }
      ],
      "rarities": [
        {
          "region": "riot",
          "rarity": 1
        }
      ]
    },
    {
      "id": 15063,
      "name": "Primal Ambush Sivir",
      "contentId": "4153b779-cfe2-41ef-a128-f5aec539bac6",
      "chromaPath": "/lol-game-data/assets/v1/champion-chroma-images/15/15063.png",
      "colors": [
        "#E58BA5",
        "#E58BA5"
      ],
      "descriptions": [],
      "rarities": [
        {
          "region": "TENCENT",
          "rarity": 1
        }
      ]
    },
    {
      "id": 15064,
      "name": "Primal Ambush Sivir",
      "contentId": "10257609-8f8c-4d98-b3bc-c3e4cbaf21e0",
      "chromaPath": "/lol-game-data/assets/v1/champion-chroma-images/15/15064.png",
      "colors": [
        "#73BFBE",
        "#73BFBE"
      ],
      "descriptions": [],
      "rarities": []
    },
    {
      "id": 15065,
      "name": "Primal Ambush Sivir",
      "contentId": "f7c9ce72-dfd1-4967-b025-3dbb65d20b25",
      "chromaPath": "/lol-game-data/assets/v1/champion-chroma-images/15/15065.png",
      "colors": [
        "#2756CE",
        "#2756CE"
      ],
      "descriptions": [],
      "rarities": []
    },
    {
      "id": 15066,
      "name": "Primal Ambush Sivir",
      "contentId": "c3a2ea0c-5465-4022-be06-c462c46f79f4",
      "chromaPath": "/lol-game-data/assets/v1/champion-chroma-images/15/15066.png",
      "colors": [
        "#2DA130",
        "#2DA130"
      ],
      "descriptions": [],
      "rarities": []
    },
    {
      "id": 15067,
      "name": "Primal Ambush Sivir",
      "contentId": "74eab779-3f5e-48f2-91fa-36424d9d6187",
      "chromaPath": "/lol-game-data/assets/v1/champion-chroma-images/15/15067.png",
      "colors": [
        "#DF9117",
        "#DF9117"
      ],
      "descriptions": [],
      "rarities": []
    },
    {
      "id": 15068,
      "name": "Primal Ambush Sivir",
      "contentId": "0147c640-0fd8-4935-8d57-a5c321c3c868",
      "chromaPath": "/lol-game-data/assets/v1/champion-chroma-images/15/15068.png",
      "colors": [
        "#9C68D7",
        "#9C68D7"
      ],
      "descriptions": [],
      "rarities": []
    },
    {
      "id": 15069,
      "name": "Primal Ambush Sivir",
      "contentId": "3ae2843e-5b88-4c75-92ea-c51e184c5b23",
      "chromaPath": "/lol-game-data/assets/v1/champion-chroma-images/15/15069.png",
      "colors": [
        "#27211C",
        "#27211C"
      ],
      "descriptions": [],
      "rarities": []
    }
  ],
  "emblems": null,
  "regionRarityId": 0,
  "rarityGemPath": null,
  "skinLines": [
    {
      "id": 200
    }
  ],
  "description": "Born into greatness, Sivir quickly discovered that her enhanced capabilities were the key to earning higher mercenary payouts. As a master of instinct, she clawed her way through countless battles and struck down any target in the way of her coin. However, her current bounty, the leader of the Favorclaw, may prove to be a beast beyond even her reach.",
  "wikiPrice": "1350",
  "wikiReleaseDate": "2024-01-24T00:00:00.000Z"
}